tkPDFViewer.py
tkpdfviewer3-1.0.1.dist-info/METADATA
tkpdfviewer3-1.0.1.dist-info/WHEEL
tkpdfviewer3-1.0.1.dist-info/top_level.txt
tkpdfviewer3-1.0.1.dist-info/RECORD
