Metadata-Version: 2.4
Name: tkpdfviewer3
Version: 1.0.1
Summary: simple tkinter PDF viewer
Author-email: Jules Lagarde <jules.lagarde@gmail.com>
Project-URL: Homepage, https://github.com/juleslagarde/tkPDFViewer3
Project-URL: Issues, https://github.com/juleslagarde/tkPDFViewer3/issues
Classifier: Programming Language :: Python :: 3
Classifier: Operating System :: OS Independent
Requires-Python: >=3.8
Requires-Dist: pillow>=10.4.0
Requires-Dist: pymupdf>=1.24.11
